LICENSE
MANIFEST.in
README.rst
setup.py
version.py
wikitoexcel/__init__.py
wikitoexcel/wikitblparser.py
wikitoexcel.egg-info/PKG-INFO
wikitoexcel.egg-info/SOURCES.txt
wikitoexcel.egg-info/dependency_links.txt
wikitoexcel.egg-info/not-zip-safe
wikitoexcel.egg-info/requires.txt
wikitoexcel.egg-info/top_level.txt