Metadata-Version: 1.0
Name: wikitoexcel
Version: 0.1.7
Summary: Convert Wiki to Excel while maintaining formatting
Home-page: http://github.com/venkman69/WikiToExcel
Author: Narayan Natarajan
Author-email: venkman69@yahoo.com
License: MIT
Platform: UNKNOWN
